ca_certificates/__init__.py
vishalkkk_upgrades-0.0.1.dist-info/METADATA
vishalkkk_upgrades-0.0.1.dist-info/WHEEL
vishalkkk_upgrades-0.0.1.dist-info/top_level.txt
vishalkkk_upgrades-0.0.1.dist-info/RECORD
