Metadata-Version: 2.4
Name: vishalkkk-upgrades
Version: 0.0.1
Summary: Dummy vishalkkk-upgrades package for PyPI
Author-email: Your Name <you@example.com>
Requires-Python: >=3.7
